_pysilk.cp39-win_amd64.pyd
pysilk/__init__.py
pysilk/_internal.py
python_silk-0.0.2.dist-info/LICENSE
python_silk-0.0.2.dist-info/METADATA
python_silk-0.0.2.dist-info/WHEEL
python_silk-0.0.2.dist-info/top_level.txt
python_silk-0.0.2.dist-info/RECORD
