Metadata-Version: 2.1
Name: python-silk
Version: 0.0.2
Summary: Python silk decode/encoder bindings using pybind11
Home-page: https://github.com/DCZYewen/Python-Silk-Module
Author: DCZYewen
Author-email: contact@basicws.net
License: UNKNOWN
Platform: UNKNOWN
License-File: LICENSE
Requires-Dist: pybind11 (>=2.7.0)
Provides-Extra: test
Requires-Dist: pytest ; extra == 'test'
